escnn/__about__.py
escnn/__init__.py
escnn/group/__init__.py
escnn/group/_clebsh_gordan.py
escnn/group/_numerical.py
escnn/group/directproduct.py
escnn/group/doublegroup.py
escnn/group/group.py
escnn/group/homspace.py
escnn/group/irrep.py
escnn/group/representation.py
escnn/group/utils.py
escnn/group/groups/__init__.py
escnn/group/groups/_numerical_thomson.py
escnn/group/groups/cyclicgroup.py
escnn/group/groups/dihedralgroup.py
escnn/group/groups/factory.py
escnn/group/groups/ico.py
escnn/group/groups/o2group.py
escnn/group/groups/o3group.py
escnn/group/groups/octa.py
escnn/group/groups/so2group.py
escnn/group/groups/so3_utils.py
escnn/group/groups/so3group.py
escnn/group/groups/utils.py
escnn/gspaces/__init__.py
escnn/gspaces/gspace.py
escnn/gspaces/r0.py
escnn/gspaces/r2.py
escnn/gspaces/r3.py
escnn/gspaces/utils.py
escnn/kernels/__init__.py
escnn/kernels/basis.py
escnn/kernels/polar_basis.py
escnn/kernels/r2.py
escnn/kernels/r3.py
escnn/kernels/spaces.py
escnn/kernels/sparse_basis.py
escnn/kernels/steerable_basis.py
escnn/kernels/utils.py
escnn/kernels/wignereckart_solver.py
escnn/nn/__init__.py
escnn/nn/field_type.py
escnn/nn/geometric_tensor.py
escnn/nn/init.py
escnn/nn/modules/__init__.py
escnn/nn/modules/branching_module.py
escnn/nn/modules/disentangle_module.py
escnn/nn/modules/equivariant_module.py
escnn/nn/modules/identity_module.py
escnn/nn/modules/linear.py
escnn/nn/modules/masking_module.py
escnn/nn/modules/merge_module.py
escnn/nn/modules/multiple_module.py
escnn/nn/modules/r2upsampling.py
escnn/nn/modules/reshuffle_module.py
escnn/nn/modules/restriction_module.py
escnn/nn/modules/sequential_module.py
escnn/nn/modules/utils.py
escnn/nn/modules/basismanager/__init__.py
escnn/nn/modules/basismanager/basisexpansion_blocks.py
escnn/nn/modules/basismanager/basisexpansion_singleblock.py
escnn/nn/modules/basismanager/basismanager.py
escnn/nn/modules/basismanager/basissampler_blocks.py
escnn/nn/modules/basismanager/basissampler_singleblock.py
escnn-0.1.4.dist-info/LICENSE
escnn-0.1.4.dist-info/METADATA
escnn-0.1.4.dist-info/WHEEL
escnn-0.1.4.dist-info/top_level.txt
escnn-0.1.4.dist-info/RECORD
