Metadata-Version: 2.1
Name: escnn
Version: 0.1.4
Summary: E(n)-Equivariant CNNs Library for PyTorch
Home-page: https://github.com/QUVA-Lab/escnn
Download-URL: https://github.com/QUVA-Lab/escnn/archive/v0.1.4.tar.gz
Author: Gabriele Cesa
Author-email: cesa.gabriele@gmail.com
License: BSD 3-Clause Clear
Keywords: pytorch,cnn,convolutional-networksequivariant,isometries
Platform: UNKNOWN
Requires-Python: >=3.7
License-File: LICENSE
Requires-Dist: torch
Requires-Dist: numpy
Requires-Dist: scipy
Requires-Dist: lie-learn
Requires-Dist: joblib
Requires-Dist: pymanopt
Requires-Dist: autograd
